AnumbyFormes/__init__.py
AnumbyFormes/__main__.py
AnumbyFormes/config.py
AnumbyFormes/pwk.py
AnumbyFormes/data/x_test.npy
AnumbyFormes/data/x_train.npy
AnumbyFormes/data/y_test.npy
AnumbyFormes/data/y_train.npy
AnumbyFormes/dataset/Coeur/RawImagesCoeur.jpg
AnumbyFormes/dataset/Eclair/RawImagesEclair.jpg
AnumbyFormes/dataset/Lune/RawImagesLune.jpg
AnumbyFormes/dataset/Rond/RawImagesRond.jpg
AnumbyFormes/dataset/Square/RawImagesSquare.jpg
AnumbyFormes/dataset/Star4/RawImagesStar4.jpg
AnumbyFormes/dataset/Star5/RawImagesStar5.jpg
AnumbyFormes/dataset/Triangle/RawImagesTriangle.jpg
AnumbyFormes/run/models/best_model.h5
AnumbyMasterMind/__init__.py
AnumbyMasterMind/__main__.py
AnumbyVehicule/__init__.py
AnumbyVehicule/__main__.py
AnumbyVehicule/fond.jpg
AnumbyRobotSJ-2.4.6.dist-info/LICENSE
AnumbyRobotSJ-2.4.6.dist-info/METADATA
AnumbyRobotSJ-2.4.6.dist-info/WHEEL
AnumbyRobotSJ-2.4.6.dist-info/entry_points.txt
AnumbyRobotSJ-2.4.6.dist-info/top_level.txt
AnumbyRobotSJ-2.4.6.dist-info/RECORD
