Metadata-Version: 2.1
Name: AnumbyRobotSJ
Version: 2.4.6
Summary: Software du Robot Anumby pour le Service Jeunesse de Bures sur Yvette 
Home-page: https://github.com/anumby-source/RobotServiceJeunesse2023/tree/main/MasterMind
Author: Chris Arnault
Author-email: chris.arnault@gmail.com
License: CeCILL-B
Classifier: License :: CeCILL-B Free Software License Agreement (CECILL-B)
Classifier: Programming Language :: Python :: 3
License-File: LICENSE
Requires-Dist: Pillow (==9.1.0)
Requires-Dist: numpy (>=1.24.2)
Requires-Dist: opencv-python (>=4.7.0)
Requires-Dist: tensorflow (>=2.11.0)
Requires-Dist: keras (>=2.11.0)
Requires-Dist: scikit-learn (>=1.2.2)
Requires-Dist: pandas (>=1.5.3)
Requires-Dist: matplotlib (>=3.7.1)
